defi_common/__init__.py
defi_common/data.py
defi_common/database/__init__.py
defi_common/database/db.py
defi_common/database/models.py
defi_common/database/services.py
defi_common/dbconfig.py
defi_common/enums.py
defi_common/exceptions.py
defi_common/time_utils.py
defi_common-0.1.96.dist-info/WHEEL
defi_common-0.1.96.dist-info/METADATA
defi_common-0.1.96.dist-info/RECORD
