Metadata-Version: 2.1
Name: defi-common
Version: 0.1.96
Summary: 
Author: Tomas Toth
Author-email: tomas.toth004@gmail.com
Requires-Python: >=3.10,<4.0
Classifier: Programming Language :: Python :: 3
Classifier: Programming Language :: Python :: 3.10
Classifier: Programming Language :: Python :: 3.11
Requires-Dist: alembic (>=1.9.2,<2.0.0)
Requires-Dist: asyncpg (>=0.27.0,<0.28.0)
Requires-Dist: fastapi-users[sqlalchemy] (>=10.3.0,<11.0.0)
Requires-Dist: pre-commit (>=2.20.0,<3.0.0)
Requires-Dist: psycopg2-binary (>=2.9.5,<3.0.0)
Requires-Dist: pydantic (>=1.10.4,<2.0.0)
Requires-Dist: pytest (>=7.2.0,<8.0.0)
Requires-Dist: python-dotenv (>=0.21.0,<0.22.0)
Requires-Dist: sqlalchemy (>=1.4.44,<2.0.0)
